{
  "permissions": {
    "api": {
      "chummy": [
        "create",
        "read",
        "update",
        "delete"
      ]
    },
    "storage": {
      "User:@model(appsync)": [
        "create",
        "read",
        "update",
        "delete"
      ],
      "Bookmark:@model(appsync)": [
        "create",
        "read",
        "update",
        "delete"
      ]
    }
  },
  "lambdaLayers": [
    {
      "type": "ProjectLayer",
      "resourceName": "chummyLambdaLayer",
      "version": 1
    }
  ]
}